[ {
  "name" : "CreatedBy",
  "dataType" : "string",
  "hasIndex" : false,
  "unique" : false,
  "primarykey" : false,
  "namefield" : false,
  "nullable" : true,
  "custom" : true,
  "createable" : true,
  "updateable" : true,
  "audit" : false,
  "customizable" : false,
  "fieldLength" : 32,
  "fieldOrder" : 8,
  "fieldProperties" : {
    "standard" : "true",
    "autoGenerated" : "false",
    "isUpdateTimeStampField" : "false",
    "isSoftDeleteField" : "false"
  }
}, {
  "name" : "CreatedDateTime",
  "dataType" : "date",
  "hasIndex" : false,
  "unique" : false,
  "primarykey" : false,
  "namefield" : false,
  "nullable" : false,
  "custom" : true,
  "createable" : false,
  "updateable" : true,
  "audit" : false,
  "customizable" : false,
  "fieldLength" : 32,
  "fieldOrder" : 10,
  "fieldProperties" : {
    "standard" : "true",
    "autoGenerated" : "false",
    "isUpdateTimeStampField" : "false",
    "isSoftDeleteField" : "false"
  }
}, {
  "name" : "email",
  "dataType" : "string",
  "hasIndex" : false,
  "unique" : false,
  "primarykey" : false,
  "namefield" : false,
  "nullable" : true,
  "custom" : true,
  "createable" : true,
  "updateable" : true,
  "audit" : false,
  "customizable" : false,
  "fieldLength" : 40,
  "fieldOrder" : 5,
  "fieldProperties" : {
    "autoGenerated" : "false"
  }
}, {
  "name" : "firstName",
  "dataType" : "string",
  "hasIndex" : false,
  "unique" : false,
  "primarykey" : false,
  "namefield" : false,
  "nullable" : true,
  "custom" : true,
  "createable" : true,
  "updateable" : true,
  "audit" : false,
  "customizable" : false,
  "fieldLength" : 40,
  "fieldOrder" : 3,
  "fieldProperties" : {
    "autoGenerated" : "false"
  }
}, {
  "name" : "id",
  "dataType" : "number",
  "hasIndex" : false,
  "unique" : true,
  "primarykey" : true,
  "namefield" : false,
  "nullable" : false,
  "custom" : true,
  "createable" : true,
  "updateable" : true,
  "audit" : false,
  "customizable" : false,
  "fieldOrder" : 1,
  "fieldProperties" : {
    "autoGenerated" : "true"
  }
}, {
  "name" : "idDoc",
  "description" : "The personal identification number relevant for fiscal and credit purposes within the country.",
  "dataType" : "string",
  "hasIndex" : false,
  "unique" : false,
  "primarykey" : false,
  "namefield" : false,
  "nullable" : false,
  "custom" : true,
  "createable" : true,
  "updateable" : true,
  "audit" : false,
  "customizable" : false,
  "fieldLength" : 40,
  "fieldOrder" : 2,
  "fieldProperties" : {
    "autoGenerated" : "false"
  }
}, {
  "name" : "lastName",
  "dataType" : "string",
  "hasIndex" : false,
  "unique" : false,
  "primarykey" : false,
  "namefield" : false,
  "nullable" : true,
  "custom" : true,
  "createable" : true,
  "updateable" : true,
  "audit" : false,
  "customizable" : false,
  "fieldLength" : 40,
  "fieldOrder" : 4,
  "fieldProperties" : {
    "autoGenerated" : "false"
  }
}, {
  "name" : "LastUpdatedBy",
  "dataType" : "string",
  "hasIndex" : false,
  "unique" : false,
  "primarykey" : false,
  "namefield" : false,
  "nullable" : true,
  "custom" : true,
  "createable" : true,
  "updateable" : true,
  "audit" : false,
  "customizable" : false,
  "fieldLength" : 32,
  "fieldOrder" : 9,
  "fieldProperties" : {
    "standard" : "true",
    "autoGenerated" : "false",
    "isUpdateTimeStampField" : "false",
    "isSoftDeleteField" : "false"
  }
}, {
  "name" : "LastUpdatedDateTime",
  "dataType" : "date",
  "hasIndex" : false,
  "unique" : false,
  "primarykey" : false,
  "namefield" : false,
  "nullable" : false,
  "custom" : true,
  "createable" : false,
  "updateable" : true,
  "audit" : false,
  "customizable" : false,
  "fieldLength" : 32,
  "fieldOrder" : 11,
  "fieldProperties" : {
    "standard" : "true",
    "autoGenerated" : "false",
    "isUpdateTimeStampField" : "true",
    "isSoftDeleteField" : "false",
    "timeStampFieldFormat" : "yyyy-MM-dd'T'HH:mm:ss.SSS"
  }
}, {
  "name" : "score",
  "dataType" : "number",
  "hasIndex" : false,
  "unique" : false,
  "primarykey" : false,
  "namefield" : false,
  "nullable" : true,
  "custom" : true,
  "createable" : true,
  "updateable" : true,
  "audit" : false,
  "customizable" : false,
  "fieldOrder" : 6,
  "fieldProperties" : {
    "autoGenerated" : "false"
  }
}, {
  "name" : "SoftDeleteFlag",
  "dataType" : "boolean",
  "hasIndex" : false,
  "unique" : false,
  "primarykey" : false,
  "namefield" : false,
  "nullable" : true,
  "custom" : true,
  "createable" : false,
  "updateable" : true,
  "audit" : false,
  "customizable" : false,
  "fieldLength" : 1,
  "fieldOrder" : 12,
  "fieldProperties" : {
    "standard" : "true",
    "autoGenerated" : "false",
    "isUpdateTimeStampField" : "false",
    "isSoftDeleteField" : "true"
  }
}, {
  "name" : "status",
  "dataType" : "string",
  "hasIndex" : false,
  "unique" : false,
  "primarykey" : false,
  "namefield" : false,
  "nullable" : true,
  "custom" : true,
  "createable" : true,
  "updateable" : true,
  "audit" : false,
  "customizable" : false,
  "fieldLength" : 100,
  "fieldOrder" : 7,
  "fieldProperties" : {
    "autoGenerated" : "false"
  }
} ]